odoo/addons/sentry/README.rst
odoo/addons/sentry/__init__.py
odoo/addons/sentry/__manifest__.py
odoo/addons/sentry/const.py
odoo/addons/sentry/logutils.py
odoo/addons/sentry/i18n/sentry.pot
odoo/addons/sentry/static/description/icon.png
odoo/addons/sentry/tests/__init__.py
odoo/addons/sentry/tests/test_client.py
odoo/addons/sentry/tests/test_logutils.py
odoo11_addon_sentry-11.0.1.1.0.dist-info/METADATA
odoo11_addon_sentry-11.0.1.1.0.dist-info/RECORD
odoo11_addon_sentry-11.0.1.1.0.dist-info/WHEEL
odoo11_addon_sentry-11.0.1.1.0.dist-info/top_level.txt
